setup.py
basic_distributions_ejm/Binomialdistribution.py
basic_distributions_ejm/Gaussiandistribution.py
basic_distributions_ejm/Generaldistribution.py
basic_distributions_ejm/__init__.py
basic_distributions_ejm.egg-info/PKG-INFO
basic_distributions_ejm.egg-info/SOURCES.txt
basic_distributions_ejm.egg-info/dependency_links.txt
basic_distributions_ejm.egg-info/not-zip-safe
basic_distributions_ejm.egg-info/top_level.txt