Metadata-Version: 1.0
Name: basic-distributions-ejm
Version: 0.1
Summary: Gaussian/Binomial distributions
Home-page: UNKNOWN
Author: Erik Mason
Author-email: ejmdpg@gmail.com
License: UNKNOWN
Platform: UNKNOWN
